easyselenium/__init__.py
easyselenium/easyselenium.py
easy_selenium_pkg-0.1.dist-info/METADATA
easy_selenium_pkg-0.1.dist-info/WHEEL
easy_selenium_pkg-0.1.dist-info/licence.txt
easy_selenium_pkg-0.1.dist-info/top_level.txt
easy_selenium_pkg-0.1.dist-info/RECORD
